aiwolf_nlp_common/__init__.py
aiwolf_nlp_common/__init__.pyi
aiwolf_nlp_common/_version.py
aiwolf_nlp_common/_version.pyi
aiwolf_nlp_common/client.py
aiwolf_nlp_common/client.pyi
aiwolf_nlp_common/packet/__init__.py
aiwolf_nlp_common/packet/__init__.pyi
aiwolf_nlp_common/packet/info.py
aiwolf_nlp_common/packet/info.pyi
aiwolf_nlp_common/packet/judge.py
aiwolf_nlp_common/packet/judge.pyi
aiwolf_nlp_common/packet/packet.py
aiwolf_nlp_common/packet/packet.pyi
aiwolf_nlp_common/packet/request.py
aiwolf_nlp_common/packet/request.pyi
aiwolf_nlp_common/packet/role.py
aiwolf_nlp_common/packet/role.pyi
aiwolf_nlp_common/packet/setting.py
aiwolf_nlp_common/packet/setting.pyi
aiwolf_nlp_common/packet/status.py
aiwolf_nlp_common/packet/status.pyi
aiwolf_nlp_common/packet/talk.py
aiwolf_nlp_common/packet/talk.pyi
aiwolf_nlp_common/packet/vote.py
aiwolf_nlp_common/packet/vote.pyi
aiwolf_nlp_common-0.6.10.dist-info/METADATA
aiwolf_nlp_common-0.6.10.dist-info/WHEEL
aiwolf_nlp_common-0.6.10.dist-info/licenses/LICENSE
aiwolf_nlp_common-0.6.10.dist-info/RECORD
