Metadata-Version: 2.4
Name: aiwolf-nlp-common
Version: 0.6.10
Summary: aiwolf-nlp-common
Project-URL: Homepage, https://aiwolfdial.github.io/aiwolf-nlp/
Author-email: aiwolfdial <aiwolf@kanolab.net>, nwatanabe <nwatanabe@kanolab.net>, ysahashi <ysahashi@kanolab.net>
Maintainer-email: aiwolfdial <aiwolf@kanolab.net>, nwatanabe <nwatanabe@kanolab.net>, ysahashi <ysahashi@kanolab.net>
License: MIT License
License-File: LICENSE
Keywords: aiwolf
Requires-Python: >=3.11
Requires-Dist: websocket-client>=1.8.0
